<annotation>
	<folder>images</folder>
	<filename>image59.PNG</filename>
	<path>C:\Users\VISION\Desktop\TPDI_carros\car-detection\dataset\images\image59.PNG</path>
	<source>
		<database>Unknown</database>
	</source>
	<size>
		<width>726</width>
		<height>507</height>
		<depth>3</depth>
	</size>
	<segmented>0</segmented>
	<object>
		<name>car</name>
		<pose>Unspecified</pose>
		<truncated>0</truncated>
		<difficult>0</difficult>
		<bndbox>
			<xmin>115</xmin>
			<ymin>102</ymin>
			<xmax>497</xmax>
			<ymax>335</ymax>
		</bndbox>
	</object>
</annotation>
