<annotation>
	<folder>images</folder>
	<filename>image465gray.png</filename>
	<path>C:\Users\flore\car-detection\dataset\images\image465gray.png</path>
	<source>
		<database>Unknown</database>
	</source>
	<size>
		<width>477</width>
		<height>395</height>
		<depth>1</depth>
	</size>
	<segmented>0</segmented>
	<object>
		<name>car</name>
		<pose>Unspecified</pose>
		<truncated>0</truncated>
		<difficult>0</difficult>
		<bndbox>
			<xmin>55</xmin>
			<ymin>64</ymin>
			<xmax>458</xmax>
			<ymax>357</ymax>
		</bndbox>
	</object>
</annotation>
