<annotation>
	<folder>images</folder>
	<filename>image590rot.png</filename>
	<path>C:\Users\flore\car-detection\dataset\images\image590rot.png</path>
	<source>
		<database>Unknown</database>
	</source>
	<size>
		<width>981</width>
		<height>981</height>
		<depth>3</depth>
	</size>
	<segmented>0</segmented>
	<object>
		<name>car</name>
		<pose>Unspecified</pose>
		<truncated>0</truncated>
		<difficult>0</difficult>
		<bndbox>
			<xmin>211</xmin>
			<ymin>186</ymin>
			<xmax>868</xmax>
			<ymax>771</ymax>
		</bndbox>
	</object>
</annotation>
