<annotation>
	<folder>images</folder>
	<filename>image546rot.png</filename>
	<path>C:\Users\flore\car-detection\dataset\images\image546rot.png</path>
	<source>
		<database>Unknown</database>
	</source>
	<size>
		<width>428</width>
		<height>428</height>
		<depth>3</depth>
	</size>
	<segmented>0</segmented>
	<object>
		<name>car</name>
		<pose>Unspecified</pose>
		<truncated>0</truncated>
		<difficult>0</difficult>
		<bndbox>
			<xmin>58</xmin>
			<ymin>119</ymin>
			<xmax>387</xmax>
			<ymax>335</ymax>
		</bndbox>
	</object>
</annotation>
