<annotation>
	<folder>images</folder>
	<filename>image350gray.png</filename>
	<path>C:\Users\Ryann\Desktop\Topicos em Processamento Digital de Images\Projeto\car-detection\dataset\images\image350gray.png</path>
	<source>
		<database>Unknown</database>
	</source>
	<size>
		<width>856</width>
		<height>572</height>
		<depth>1</depth>
	</size>
	<segmented>0</segmented>
	<object>
		<name>car</name>
		<pose>Unspecified</pose>
		<truncated>0</truncated>
		<difficult>0</difficult>
		<bndbox>
			<xmin>113</xmin>
			<ymin>86</ymin>
			<xmax>661</xmax>
			<ymax>409</ymax>
		</bndbox>
	</object>
</annotation>
